LICENSE
MANIFEST.in
README.md
setup.py
vqc_lite/__init__.py
vqc_lite.egg-info/PKG-INFO
vqc_lite.egg-info/SOURCES.txt
vqc_lite.egg-info/dependency_links.txt
vqc_lite.egg-info/requires.txt
vqc_lite.egg-info/top_level.txt
vqc_lite/circuit_stack/__init__.py
vqc_lite/circuit_stack/block.py
vqc_lite/circuit_stack/circuit.py
vqc_lite/circuit_stack/circuit_mps.py
vqc_lite/circuit_stack/gate.py
vqc_lite/circuit_stack/layer.py
vqc_lite/circuit_stack_pennylane/__init__.py
vqc_lite/circuit_stack_pennylane/block.py
vqc_lite/circuit_stack_pennylane/circuit.py
vqc_lite/circuit_stack_pennylane/circuit_mps.py
vqc_lite/experiments/__init__.py
vqc_lite/experiments/expressibility.py
vqc_lite/experiments/state_preparation.py
vqc_lite/toolboxes/__init__.py
vqc_lite/toolboxes/toolbox_statevector.py