Metadata-Version: 2.1
Name: vqc-lite
Version: 0.1.0
Summary: vqc_lite: A reader-friendly Python implementation of Variational Quantum Circuits (VQC) based on Jax and Pennylane
Home-page: https://github.com/kevinkayyy/VQC-Lite
Author: Kevin Shen
Author-email: kevinshen.abcd@gmail.com
License: Apache-2.0
Platform: UNKNOWN
License-File: LICENSE
